tinydbwrapper/__init__.py
tinydbwrapper-0.1.0.dist-info/METADATA
tinydbwrapper-0.1.0.dist-info/WHEEL
tinydbwrapper-0.1.0.dist-info/RECORD
