Metadata-Version: 2.1
Name: tinydbwrapper
Version: 0.1.0
Summary: A wrapper around TinyDB for easy JSON serialization and deserialization
Author: Nik Sharma
Author-email: sharma7n@gmail.com
Requires-Python: >=3.7,<4.0
Classifier: Programming Language :: Python :: 3
Classifier: Programming Language :: Python :: 3.7
Classifier: Programming Language :: Python :: 3.8
Classifier: Programming Language :: Python :: 3.9
Classifier: Programming Language :: Python :: 3.10
Classifier: Programming Language :: Python :: 3.11
Classifier: Programming Language :: Python :: 3.12
Requires-Dist: tinydb (>=4.8.0,<5.0.0)
